main.py
VoiceDunkinDonut-1.0.0.dist-info/METADATA
VoiceDunkinDonut-1.0.0.dist-info/WHEEL
VoiceDunkinDonut-1.0.0.dist-info/entry_points.txt
VoiceDunkinDonut-1.0.0.dist-info/top_level.txt
VoiceDunkinDonut-1.0.0.dist-info/RECORD
